{
  "api_url": "inherit",
  "api_key": "",
  "dictionary": [
    "Async",
    "Bugfix",
    "CHANGELOG",
    "CircleCI",
    "Codecov",
    "ESLint",
    "JS",
    "JSDocs",
    "NPM",
    "README",
    "TSLint",
    "VSCodium",
    "api",
    "async",
    "benchmarking",
    "benny",
    "changelog",
    "const",
    "gitattributes",
    "gitignore",
    "iframe",
    "js",
    "json",
    "linter",
    "npm",
    "prepublish",
    "typings"
  ],
  "language": "en-US",
  "rules": {
    "casing": false,
    "colloquialisms": true,
    "compounding": true,
    "confused_words": true,
    "false_friends": true,
    "gender_neutrality": true,
    "grammar": true,
    "misc": true,
    "punctuation": false,
    "redundancy": true,
    "regionalisms": true,
    "repetitions": true,
    "semantics": true,
    "style": true,
    "typography": false,
    "typos": true
  }
}